README.md
setup.py
cif/__init__.py
cif/cif.py
cif.egg-info/PKG-INFO
cif.egg-info/SOURCES.txt
cif.egg-info/dependency_links.txt
cif.egg-info/requires.txt
cif.egg-info/top_level.txt