Metadata-Version: 2.1
Name: cif
Version: 0.0.6
Summary: Composite Indicators Framework for Business Cycle Analysis
Home-page: https://github.com/LenkaV/CIF
Author: Lenka Vraná
Author-email: lenka.vrana@gmail.com
License: gpl-3.0
Keywords: business cycle analysis,composite indicators,OECD data download
Platform: UNKNOWN
Requires-Python: >=3, <4
